scrapy_s3logstorage/__init__.py
scrapy_s3logstorage/extension.py
scrapy_s3logstorage-0.1.1.dist-info/LICENSE
scrapy_s3logstorage-0.1.1.dist-info/METADATA
scrapy_s3logstorage-0.1.1.dist-info/WHEEL
scrapy_s3logstorage-0.1.1.dist-info/RECORD
