Metadata-Version: 2.1
Name: scrapy-s3logstorage
Version: 0.1.1
Summary: Upload scrapy logs to S3
Author: Nicholas Mischke
Author-email: nmischkework@proton.me
Requires-Python: >=3.7,<4.0
Classifier: Programming Language :: Python :: 3
Classifier: Programming Language :: Python :: 3.7
Classifier: Programming Language :: Python :: 3.8
Classifier: Programming Language :: Python :: 3.9
Classifier: Programming Language :: Python :: 3.10
Classifier: Programming Language :: Python :: 3.11
Requires-Dist: botocore (>=1.29.143,<2.0.0)
Requires-Dist: environs (>=9.5.0,<10.0.0)
Requires-Dist: scrapy (>=2.9.0,<3.0.0)
